connection_manager/__init__.py
connection_manager/aws_connection.py
connection_manager/config_manager.py
connection_manager/oracle_connection.py
connection_manager/redshift_connection.py
connection_manager/tableau_connection.py
connection_manager-1.1.0.dist-info/METADATA
connection_manager-1.1.0.dist-info/WHEEL
connection_manager-1.1.0.dist-info/top_level.txt
connection_manager-1.1.0.dist-info/RECORD
